bma_opendata/__init__.py
bma_opendata/client.py
bma_opendata/models.py
bma_opendata-0.1.0.dist-info/licenses/LICENSE
bma_opendata-0.1.0.dist-info/METADATA
bma_opendata-0.1.0.dist-info/WHEEL
bma_opendata-0.1.0.dist-info/top_level.txt
bma_opendata-0.1.0.dist-info/RECORD
