Metadata-Version: 2.4
Name: bma-opendata
Version: 0.1.0
Summary: Typed SDK for the Bangkok Open Data CKAN Action API
Author: Sirin Puenggun
License: MIT License
Project-URL: Homepage, https://github.com/Sosokker/bma-opendata-python-sdk
Project-URL: Documentation, https://github.com/Sosokker/bma-opendata-python-sdk#readme
Project-URL: Repository, https://github.com/Sosokker/bma-opendata-python-sdk
Project-URL: Issues, https://github.com/Sosokker/bma-opendata-python-sdk/issues
Keywords: ckan,bangkok,open data,sdk,api
Classifier: Development Status :: 3 - Alpha
Classifier: Intended Audience :: Developers
Classifier: Topic :: Internet :: WWW/HTTP
Classifier: Topic :: Software Development :: Libraries
Classifier: License :: OSI Approved :: MIT License
Classifier: Programming Language :: Python :: 3
Classifier: Programming Language :: Python :: 3.13
Classifier: Operating System :: OS Independent
Requires-Python: >=3.13
License-File: LICENSE
Requires-Dist: pydantic<3.0,>=2.5
Requires-Dist: requests<3.0,>=2.31
Dynamic: license-file
